MANIFEST.in
setup.py
dagobah/__init__.py
dagobah/functions.py
dagobah/nagobah.py
dagobah/backend/__init__.py
dagobah/backend/base.py
dagobah/backend/mongo.py
dagobah/core/__init__.py
dagobah/core/components.py
dagobah/core/core.py
dagobah/daemon/__init__.py
dagobah/daemon/api.py
dagobah/daemon/app.py
dagobah/daemon/auth.py
dagobah/daemon/daemon.py
dagobah/daemon/dagobahd.yml
dagobah/daemon/util.py
dagobah/daemon/views.py
dagobah/daemon/static/.gitignore
dagobah/daemon/static/css/job_detail.css
dagobah/daemon/static/css/job_graph.css
dagobah/daemon/static/css/jobs.css
dagobah/daemon/static/css/kickstrap.css
dagobah/daemon/static/css/log_detail.css
dagobah/daemon/static/css/login.css
dagobah/daemon/static/css/settings.css
dagobah/daemon/static/css/site.css
dagobah/daemon/static/css/task_detail.css
dagobah/daemon/static/img/favicon.ico
dagobah/daemon/static/js/job_detail.js
dagobah/daemon/static/js/job_graph.js
dagobah/daemon/static/js/job_model.js
dagobah/daemon/static/js/jobs.js
dagobah/daemon/static/js/log_detail.js
dagobah/daemon/static/js/navbar.js
dagobah/daemon/static/js/settings.js
dagobah/daemon/static/js/site.js
dagobah/daemon/static/js/task_detail.js
dagobah/daemon/static/lib/bootbox.min.js
dagobah/daemon/static/lib/d3.v3.min.js
dagobah/daemon/static/lib/handlebars.js
dagobah/daemon/static/lib/moment.min.js
dagobah/daemon/static/lib/Kickstrap1.3.2/index.html
dagobah/daemon/static/lib/Kickstrap1.3.2/kickstrap.less
dagobah/daemon/static/lib/Kickstrap1.3.2/theme.less
dagobah/daemon/static/lib/Kickstrap1.3.2/Kickstrap/qunit.zip
dagobah/daemon/static/lib/Kickstrap1.3.2/Kickstrap/apps/bootstrap/bootstrap.js
dagobah/daemon/static/lib/Kickstrap1.3.2/Kickstrap/apps/bootstrap/bootstrap.min.js
dagobah/daemon/static/lib/Kickstrap1.3.2/Kickstrap/apps/bootstrap/config.ks
dagobah/daemon/static/lib/Kickstrap1.3.2/Kickstrap/apps/bootstrap/affix/config.ks
dagobah/daemon/static/lib/Kickstrap1.3.2/Kickstrap/apps/bootstrap/alert/advisory.js
nagobah_with_server.egg-info/PKG-INFO
nagobah_with_server.egg-info/SOURCES.txt
nagobah_with_server.egg-info/dependency_links.txt
nagobah_with_server.egg-info/entry_points.txt
nagobah_with_server.egg-info/not-zip-safe
nagobah_with_server.egg-info/requires.txt
nagobah_with_server.egg-info/top_level.txt