Metadata-Version: 1.1
Name: nagobah-with-server
Version: 0.0.3
Summary: Simple DAG-based job scheduler, expanded batch mode by xuanxuan
Home-page: https://github.com/littlegump/dagobah
Author: Travis Thieman & a little bit with xuanxuan
Author-email: travis.thieman@gmail.com; 13060404095@163.com
License: WTFPL
Download-URL: https://github.com/littlegump/dagobah/tarball/0.1.5
Platform: UNKNOWN
